volkszaehler/__init__.py
volkszaehler/exceptions.py
volkszaehler-0.3.2.dist-info/LICENSE
volkszaehler-0.3.2.dist-info/METADATA
volkszaehler-0.3.2.dist-info/WHEEL
volkszaehler-0.3.2.dist-info/top_level.txt
volkszaehler-0.3.2.dist-info/zip-safe
volkszaehler-0.3.2.dist-info/RECORD
