Metadata-Version: 2.1
Name: volkszaehler
Version: 0.3.2
Summary: Python Wrapper for interacting with the Volkszahler API.
Home-page: https://github.com/home-assistant-ecosystem/python-volkszaehler
Author: Fabian Affolter
Author-email: fabian@affolter-engineering.ch
License: MIT
Download-URL: https://github.com/home-assistant-ecosystem/python-volkszaehler/releases
Platform: UNKNOWN
Classifier: Development Status :: 3 - Alpha
Classifier: Environment :: Console
Classifier: Intended Audience :: Developers
Classifier: License :: OSI Approved :: MIT License
Classifier: Operating System :: MacOS :: MacOS X
Classifier: Operating System :: Microsoft :: Windows
Classifier: Operating System :: POSIX
Classifier: Programming Language :: Python :: 3.8
Classifier: Programming Language :: Python :: 3.9
Classifier: Topic :: Utilities
Requires-Python: >=3.8
License-File: LICENSE
Requires-Dist: aiohttp (<4,>=3.7.4)
Requires-Dist: async-timeout (<5,>4)
